seleniumrequests/__init__.py
seleniumrequests/request.py
selenium_requests-2.0.1.dist-info/LICENSE
selenium_requests-2.0.1.dist-info/WHEEL
selenium_requests-2.0.1.dist-info/METADATA
selenium_requests-2.0.1.dist-info/RECORD
