Metadata-Version: 2.1
Name: selenium-requests
Version: 2.0.1
Summary: Extends Selenium WebDriver classes to include the request function from the Requests library, while doing all the needed cookie and request headers handling.
Author: Chris Braun
Author-email: cryzed@googlemail.com
Requires-Python: >=3.7,<4.0
Classifier: Programming Language :: Python :: 3
Classifier: Programming Language :: Python :: 3.7
Classifier: Programming Language :: Python :: 3.8
Classifier: Programming Language :: Python :: 3.9
Classifier: Programming Language :: Python :: 3.10
Classifier: Programming Language :: Python :: 3.11
Requires-Dist: requests (>=2.26.0,<3.0.0)
Requires-Dist: selenium (>=4.3.0,<5.0.0)
Requires-Dist: tldextract (>=3.1.1,<4.0.0)
